{
    "product_data": {
        "id": 105,
        "category_id": 19,
        "parent_product_id": null,
        "product_brand_id": null,
        "product_type": null,
        "title": "Horseshoe Jeans",
        "sapphire_series": null,
        "sapphire_sort_order": "",
        "slug": "horseshoe-jeans",
        "subtitle": "Horseshoe Jeans",
        "short_desc": "",
        "description": "",
        "price": 0,
        "image_size": "",
        "is_featured": null,
        "is_archived": 0,
        "is_copy": 0,
        "identifier": "horseshoe-jeans",
        "template": "",
        "sort_order": 61,
        "feature_sort_order": 0,
        "status": 1,
        "title_tag": "",
        "meta_title": "",
        "meta_description": "",
        "og_title": "",
        "og_description": "",
        "preview": null,
        "instructions": null,
        "created_at": "2025-05-04 09:26:51",
        "updated_at": "2025-05-19 12:46:07",
        "created_by": 1,
        "updated_by": 1,
        "type": "",
        "location": null,
        "area": "",
        "category_title": "Women",
        "category_slug": "women"
    },
    "images": {
        "list": [
            {
                "id": 1173,
                "identifier_type": "Product",
                "identifier_id": 105,
                "short_title": "",
                "short_desc": "",
                "img_alt": "",
                "path": "uploads\/product\/horseshoe-jeans\/",
                "cloud_path": null,
                "img_name": "1747635949Yv2Mg.jpg",
                "real_name": null,
                "full_path": "https:\/\/cms.ecosourcing.org\/admin\/uploads\/product\/horseshoe-jeans\/1747635949Yv2Mg.jpg",
                "cdn_path": "1747635949Yv2Mg.jpg",
                "thumb": "on"
            },
            {
                "id": 1083,
                "identifier_type": "Product",
                "identifier_id": 105,
                "short_title": "",
                "short_desc": "",
                "img_alt": "",
                "path": "uploads\/product\/horseshoe-jeans\/",
                "cloud_path": null,
                "img_name": "1746350827KByEz.jpg",
                "real_name": null,
                "full_path": "https:\/\/cms.ecosourcing.org\/admin\/uploads\/product\/horseshoe-jeans\/1746350827KByEz.jpg",
                "cdn_path": "1746350827KByEz.jpg"
            },
            {
                "id": 1084,
                "identifier_type": "Product",
                "identifier_id": 105,
                "short_title": null,
                "short_desc": null,
                "img_alt": null,
                "path": "uploads\/product\/horseshoe-jeans\/",
                "cloud_path": null,
                "img_name": "1746350827gEd4O.jpg",
                "real_name": null,
                "full_path": "https:\/\/cms.ecosourcing.org\/admin\/uploads\/product\/horseshoe-jeans\/1746350827gEd4O.jpg",
                "cdn_path": "1746350827gEd4O.jpg"
            },
            {
                "id": 1085,
                "identifier_type": "Product",
                "identifier_id": 105,
                "short_title": null,
                "short_desc": null,
                "img_alt": null,
                "path": "uploads\/product\/horseshoe-jeans\/",
                "cloud_path": null,
                "img_name": "1746350827y0cAU.jpg",
                "real_name": null,
                "full_path": "https:\/\/cms.ecosourcing.org\/admin\/uploads\/product\/horseshoe-jeans\/1746350827y0cAU.jpg",
                "cdn_path": "1746350827y0cAU.jpg"
            }
        ],
        "count": 4
    },
    "files": {
        "list": [],
        "count": 0
    },
    "posts": {
        "list": [],
        "count": 0
    },
    "galleries": {
        "count": 0
    },
    "variations": "",
    "specifications": []
}